chesscom_game_fetcher/__init__.py
chesscom_game_fetcher/fetcher.py
chesscom_game_fetcher-1.1.0.dist-info/METADATA
chesscom_game_fetcher-1.1.0.dist-info/WHEEL
chesscom_game_fetcher-1.1.0.dist-info/licenses/LICENSE
chesscom_game_fetcher-1.1.0.dist-info/RECORD
