Metadata-Version: 2.3
Name: chesscom-game-fetcher
Version: 1.1.0
Summary: Fetches all games from chess.com for a specified period at a defined time control between players above a defined rating.
Project-URL: Homepage, https://github.com/YetiFace/chesscom-game-fetcher
Author-email: Scott Oxtoby <pypi@oxtoby.uk>
License-File: LICENSE
Classifier: License :: OSI Approved :: MIT License
Classifier: Operating System :: OS Independent
Classifier: Programming Language :: Python :: 3
Requires-Python: >=3.8
Requires-Dist: prettytable
Requires-Dist: python-dateutil
Requires-Dist: requests
